flask_template_support/__init__.py
flask_template_support/filters.py
flask_template_support/functions.py
flask_template_support/template_support.py
flask_template_support/version.py
Flask_TemplateSupport-2.0.1.dist-info/LICENSE
Flask_TemplateSupport-2.0.1.dist-info/METADATA
Flask_TemplateSupport-2.0.1.dist-info/WHEEL
Flask_TemplateSupport-2.0.1.dist-info/top_level.txt
Flask_TemplateSupport-2.0.1.dist-info/RECORD
